<?xml version="1.0" encoding="UTF-8"?>
<!DOCTYPE mapper PUBLIC "-//mybatis.org//DTD Mapper 3.0//EN" "http://mybatis.org/dtd/mybatis-3-mapper.dtd">
<mapper namespace="com.jingdianjichi.practice.server.dao.PracticeSetDao">

    <resultMap type="com.jingdianjichi.practice.server.entity.PracticeSet" id="PracticeSetMap">
        <result property="id" column="id" jdbcType="INTEGER"/>
        <result property="setName" column="set_name" jdbcType="VARCHAR"/>
        <result property="setType" column="set_type" jdbcType="INTEGER"/>
        <result property="setHeat" column="set_heat" jdbcType="INTEGER"/>
        <result property="setDesc" column="set_desc" jdbcType="VARCHAR"/>
        <result property="primaryCategoryId" column="primary_category_id" jdbcType="INTEGER"/>
        <result property="createdBy" column="created_by" jdbcType="VARCHAR"/>
        <result property="createdTime" column="created_time" jdbcType="TIMESTAMP"/>
        <result property="updateBy" column="update_by" jdbcType="VARCHAR"/>
        <result property="updateTime" column="update_time" jdbcType="TIMESTAMP"/>
        <result property="isDeleted" column="is_deleted" jdbcType="INTEGER"/>
    </resultMap>

    <!--查询单个-->
    <select id="queryById" resultMap="PracticeSetMap">
        select id,
               set_name,
               set_type,
               set_heat,
               set_desc,
               primary_category_id,
               created_by,
               created_time,
               update_by,
               update_time,
               is_deleted
        from practice_set
        where id = #{id}
          and is_deleted = 0
    </select>

    <!--通过实体作为筛选条件查询-->
    <select id="queryByPage" resultMap="PracticeSetMap">
        select * from practice_set
        <where>
            <if test="entity.id != null">
                and id = #{entity.id}
            </if>
            <if test="entity.setName != null and entity.setName != ''">
                and set_name = #{entity.setName}
            </if>
            <if test="entity.setType != null">
                and set_type = #{entity.setType}
            </if>
            <if test="entity.setHeat != null">
                and set_heat = #{entity.setHeat}
            </if>
            <if test="entity.setDesc != null and entity.setDesc != ''">
                and set_desc = #{entity.setDesc}
            </if>
            <if test="entity.primaryCategoryId != null">
                and primary_category_id = #{entity.primaryCategoryId}
            </if>
            <if test="entity.createdBy != null and entity.createdBy != ''">
                and created_by = #{entity.createdBy}
            </if>
            <if test="entity.createdTime != null">
                and created_time = #{entity.createdTime}
            </if>
            <if test="entity.updateBy != null and entity.updateBy != ''">
                and update_by = #{entity.updateBy}
            </if>
            <if test="entity.updateTime != null">
                and update_time = #{entity.updateTime}
            </if>
            <if test="entity.isDeleted != null">
                and is_deleted = #{entity.isDeleted}
            </if>
        </where>
        limit #{start}, #{size}
    </select>

    <!--统计总行数-->
    <select id="count" resultType="java.lang.Long">
        select count(1)
        from practice_set
        <where>
            <if test="id != null">
                and id = #{id}
            </if>
            <if test="setName != null and setName != ''">
                and set_name = #{setName}
            </if>
            <if test="setType != null">
                and set_type = #{setType}
            </if>
            <if test="setHeat != null">
                and set_heat = #{setHeat}
            </if>
            <if test="setDesc != null and setDesc != ''">
                and set_desc = #{setDesc}
            </if>
            <if test="primaryCategoryId != null">
                and primary_category_id = #{primaryCategoryId}
            </if>
            <if test="createdBy != null and createdBy != ''">
                and created_by = #{createdBy}
            </if>
            <if test="createdTime != null">
                and created_time = #{createdTime}
            </if>
            <if test="updateBy != null and updateBy != ''">
                and update_by = #{updateBy}
            </if>
            <if test="updateTime != null">
                and update_time = #{updateTime}
            </if>
            <if test="isDeleted != null">
                and is_deleted = #{isDeleted}
            </if>
        </where>
    </select>

    <select id="queryPreSetContent" resultType="com.jingdianjichi.practice.server.entity.PracticeSet">
        select *
        from practice_set
        where is_deleted = 0
        and set_type = 2
        <if test="setName != null">
            and set_name like concat('%',#{setName,jdbcType=VARCHAR},'%')
        </if>
        <if test="orderType != null and orderType == 1">
            order by set_name desc
        </if>
        <if test="orderType != null and orderType == 2">
            order by created_time desc
        </if>
        <if test="orderType != null and orderType == 3">
            order by set_heat desc
        </if>
        limit #{start}, #{pageSize}
    </select>


    <!--新增所有列-->
    <insert id="insert" keyProperty="id" useGeneratedKeys="true">
        insert into practice_set(set_name, set_type, set_heat, set_desc, primary_category_id, created_by, created_time,
                                 update_by, update_time, is_deleted)
        values (#{setName}, #{setType}, #{setHeat}, #{setDesc}, #{primaryCategoryId}, #{createdBy}, #{createdTime},
                #{updateBy}, #{updateTime}, #{isDeleted})
    </insert>

    <insert id="insertBatch" keyProperty="id" useGeneratedKeys="true">
        insert into practice_set(set_name, set_type, set_heat, set_desc, primary_category_id, created_by, created_time,
        update_by, update_time, is_deleted)
        values
        <foreach collection="entities" item="entity" separator=",">
            (#{entity.setName}, #{entity.setType}, #{entity.setHeat}, #{entity.setDesc}, #{entity.primaryCategoryId},
            #{entity.createdBy}, #{entity.createdTime}, #{entity.updateBy}, #{entity.updateTime}, #{entity.isDeleted})
        </foreach>
    </insert>

    <insert id="insertOrUpdateBatch" keyProperty="id" useGeneratedKeys="true">
        insert into practice_set(set_name, set_type, set_heat, set_desc, primary_category_id, created_by, created_time,
        update_by, update_time, is_deleted)
        values
        <foreach collection="entities" item="entity" separator=",">
            (#{entity.setName}, #{entity.setType}, #{entity.setHeat}, #{entity.setDesc}, #{entity.primaryCategoryId},
            #{entity.createdBy}, #{entity.createdTime}, #{entity.updateBy}, #{entity.updateTime}, #{entity.isDeleted})
        </foreach>
        on duplicate key update
        set_name = values(set_name),
        set_type = values(set_type),
        set_heat = values(set_heat),
        set_desc = values(set_desc),
        primary_category_id = values(primary_category_id),
        created_by = values(created_by),
        created_time = values(created_time),
        update_by = values(update_by),
        update_time = values(update_time),
        is_deleted = values(is_deleted)
    </insert>

    <!--通过主键修改数据-->
    <update id="update">
        update practice_set
        <set>
            <if test="setName != null and setName != ''">
                set_name = #{setName},
            </if>
            <if test="setType != null">
                set_type = #{setType},
            </if>
            <if test="setHeat != null">
                set_heat = #{setHeat},
            </if>
            <if test="setDesc != null and setDesc != ''">
                set_desc = #{setDesc},
            </if>
            <if test="primaryCategoryId != null">
                primary_category_id = #{primaryCategoryId},
            </if>
            <if test="createdBy != null and createdBy != ''">
                created_by = #{createdBy},
            </if>
            <if test="createdTime != null">
                created_time = #{createdTime},
            </if>
            <if test="updateBy != null and updateBy != ''">
                update_by = #{updateBy},
            </if>
            <if test="updateTime != null">
                update_time = #{updateTime},
            </if>
            <if test="isDeleted != null">
                is_deleted = #{isDeleted},
            </if>
        </set>
        where id = #{id}
    </update>

    <!--通过主键删除-->
    <update id="deleteById">
        update practice_set
        set is_deleted = 1
        where id = #{id}
    </update>

    <!--  增加热度  -->
    <update id="upHeat">
        update practice_set
        set set_heat = set_heat + 1
        where id = #{id}
    </update>

</mapper>

